intercepts/__init__.py
intercepts/__version__.py
intercepts/registration.py
intercepts/_introspection/__init__.py
intercepts/_introspection/linux.py
intercepts/_introspection/windows.py
intercepts-0.4.0.dist-info/LICENSE
intercepts-0.4.0.dist-info/METADATA
intercepts-0.4.0.dist-info/WHEEL
intercepts-0.4.0.dist-info/top_level.txt
intercepts-0.4.0.dist-info/RECORD
