Metadata-Version: 2.1
Name: intercepts
Version: 0.4.0
Summary: Intercept function and method calls
Author-email: David Shriver <davidshriver@outlook.com>
License: MIT
Project-URL: Source, https://github.com/dlshriver/intercepts
Project-URL: Documentation, https://intercepts.readthedocs.io/en/latest/
Project-URL: Issues, https://github.com/dlshriver/intercepts/issues
Keywords: development,intercepts,testing
Classifier: Development Status :: 3 - Alpha
Classifier: Intended Audience :: Developers
Classifier: License :: OSI Approved :: MIT License
Classifier: Programming Language :: Python :: 3
Classifier: Programming Language :: Python :: 3.7
Classifier: Programming Language :: Python :: 3.8
Classifier: Programming Language :: Python :: 3.9
Classifier: Programming Language :: Python :: 3.10
Classifier: Programming Language :: Python :: 3.11
Classifier: Topic :: Software Development :: Testing
Requires-Python: >=3.7
License-File: LICENSE
Provides-Extra: dev
Requires-Dist: mypy (~=1.0.0) ; extra == 'dev'
Requires-Dist: black (~=23.1.0) ; extra == 'dev'
Requires-Dist: isort (~=5.12.0) ; extra == 'dev'
Requires-Dist: coverage (~=7.1.0) ; extra == 'dev'
Requires-Dist: pytest (~=7.2.1) ; extra == 'dev'
Provides-Extra: docs
Requires-Dist: furo (~=2022.12.7) ; extra == 'docs'
Requires-Dist: sphinx (~=6.1.3) ; extra == 'docs'
Provides-Extra: lint
Requires-Dist: mypy (~=1.0.0) ; extra == 'lint'
Provides-Extra: style
Requires-Dist: black (~=23.1.0) ; extra == 'style'
Requires-Dist: isort (~=5.12.0) ; extra == 'style'
Provides-Extra: test
Requires-Dist: coverage (~=7.1.0) ; extra == 'test'
Requires-Dist: pytest (~=7.2.1) ; extra == 'test'
